{
  "config": "fusioncharts_export.json",
  "chartConfig": "fusioncharts_chart.json",
  "chartConfigOptions": {},
  "inputFile": "chart.svg",
  "outputFile": "export--<%= number(1) %>.png",
  "outputAsZip": "true",
  "type": "png",
  "callbacks": "fusioncharts_export_callbacks.js",
  "template": "template.html",
  "resources": "resources.json",
  "logDest": "/",
  "logFile": "fusioncharts_export.log",
  "logLevel": 7,
  "remoteExportEnabled": "false",
  "exportUrl": "http://export.api3.fusioncharts.com",
  "exportLogUrl": "http://export.api3.fusioncharts.com/api/v1.0/logs"
}
